pulse_ssz/__init__.py
pulse_ssz/abc.py
pulse_ssz/codec.py
pulse_ssz/constants.py
pulse_ssz/exceptions.py
pulse_ssz/hash.py
pulse_ssz/hash_tree.py
pulse_ssz/hashable_container.py
pulse_ssz/hashable_list.py
pulse_ssz/hashable_structure.py
pulse_ssz/hashable_vector.py
pulse_ssz/tree_hash.py
pulse_ssz/typing.py
pulse_ssz/utils.py
pulse_ssz/cache/__init__.py
pulse_ssz/cache/cache.py
pulse_ssz/cache/utils.py
pulse_ssz/sedes/__init__.py
pulse_ssz/sedes/base.py
pulse_ssz/sedes/basic.py
pulse_ssz/sedes/bitlist.py
pulse_ssz/sedes/bitvector.py
pulse_ssz/sedes/boolean.py
pulse_ssz/sedes/byte.py
pulse_ssz/sedes/byte_list.py
pulse_ssz/sedes/byte_vector.py
pulse_ssz/sedes/container.py
pulse_ssz/sedes/list.py
pulse_ssz/sedes/serializable.py
pulse_ssz/sedes/signed_serializable.py
pulse_ssz/sedes/string.py
pulse_ssz/sedes/uint.py
pulse_ssz/sedes/vector.py
pulse_ssz/tools/__init__.py
pulse_ssz/tools/codec.py
pulse_ssz/tools/dump.py
pulse_ssz/tools/parse.py
pulse_ssz-0.4.0.dist-info/LICENSE
pulse_ssz-0.4.0.dist-info/METADATA
pulse_ssz-0.4.0.dist-info/WHEEL
pulse_ssz-0.4.0.dist-info/top_level.txt
pulse_ssz-0.4.0.dist-info/RECORD
