Metadata-Version: 2.1
Name: pulse-ssz
Version: 0.4.0
Summary: pulse-ssz: Python implementation of the Simple Serialization encoding and decoding
Home-page: https://gitlab.com/aggris2/py-pulse-ssz
Author: PulseChain team
Author-email: aggris2@gmail.com
License: MIT
Keywords: pulsechain
Classifier: Development Status :: 3 - Alpha
Classifier: Intended Audience :: Developers
Classifier: License :: OSI Approved :: MIT License
Classifier: Natural Language :: English
Classifier: Operating System :: MacOS
Classifier: Operating System :: POSIX
Classifier: Programming Language :: Python :: 3
Classifier: Programming Language :: Python :: 3.7
Classifier: Programming Language :: Python :: 3.8
Classifier: Programming Language :: Python :: 3.9
Classifier: Programming Language :: Python :: 3.10
Classifier: Programming Language :: Python :: Implementation :: PyPy
Requires-Python: >=3.7, <4
License-File: LICENSE
Requires-Dist: eth-utils (<2,>=1)
Requires-Dist: lru-dict (>=1.1.6)
Requires-Dist: pyrsistent (<0.17,>=0.16.0)
Provides-Extra: dev
Requires-Dist: bumpversion (<1,>=0.5.3) ; extra == 'dev'
Requires-Dist: wheel ; extra == 'dev'
Requires-Dist: twine ; extra == 'dev'
Requires-Dist: ipython ; extra == 'dev'
Requires-Dist: pre-commit (==1.18.3) ; extra == 'dev'
Requires-Dist: pytest-watch (<5,>=4.1.0) ; extra == 'dev'
Requires-Dist: pytest (<7,>=6.2.5) ; extra == 'dev'
Requires-Dist: pytest-xdist (<3,>=2.4.0) ; extra == 'dev'
Requires-Dist: tox (==3.14.6) ; extra == 'dev'
Requires-Dist: hypothesis (==4.54.0) ; extra == 'dev'
Requires-Dist: mypy-extensions (<1.0.0,>=0.4.1) ; extra == 'dev'
Requires-Dist: black (<23,>=22.6.0) ; extra == 'dev'
Requires-Dist: flake8 (==3.7.9) ; extra == 'dev'
Requires-Dist: isort (<6,>=5.10.1) ; extra == 'dev'
Requires-Dist: pydocstyle (<6,>=5.0.0) ; extra == 'dev'
Requires-Dist: Sphinx (<2,>=1.6.5) ; extra == 'dev'
Requires-Dist: sphinx-rtd-theme (<1,>=0.1.9) ; extra == 'dev'
Requires-Dist: Jinja2 (<3) ; extra == 'dev'
Requires-Dist: MarkupSafe (<2) ; extra == 'dev'
Requires-Dist: towncrier (<22,>=21) ; extra == 'dev'
Requires-Dist: ruamel.yaml (==0.17.21) ; extra == 'dev'
Provides-Extra: doc
Requires-Dist: Sphinx (<2,>=1.6.5) ; extra == 'doc'
Requires-Dist: sphinx-rtd-theme (<1,>=0.1.9) ; extra == 'doc'
Requires-Dist: Jinja2 (<3) ; extra == 'doc'
Requires-Dist: MarkupSafe (<2) ; extra == 'doc'
Requires-Dist: towncrier (<22,>=21) ; extra == 'doc'
Provides-Extra: lint
Requires-Dist: black (<23,>=22.6.0) ; extra == 'lint'
Requires-Dist: flake8 (==3.7.9) ; extra == 'lint'
Requires-Dist: isort (<6,>=5.10.1) ; extra == 'lint'
Requires-Dist: pydocstyle (<6,>=5.0.0) ; extra == 'lint'
Provides-Extra: test
Requires-Dist: pytest (<7,>=6.2.5) ; extra == 'test'
Requires-Dist: pytest-xdist (<3,>=2.4.0) ; extra == 'test'
Requires-Dist: tox (==3.14.6) ; extra == 'test'
Requires-Dist: hypothesis (==4.54.0) ; extra == 'test'
Requires-Dist: mypy-extensions (<1.0.0,>=0.4.1) ; extra == 'test'
Provides-Extra: yaml
Requires-Dist: ruamel.yaml (==0.17.21) ; extra == 'yaml'
